mcp_xiaohongshu_kel/__init__.py
mcp_xiaohongshu_kel/__main__.py
mcp_xiaohongshu_kel/server.py
mcp_xiaohongshu_kel-0.1.0.dist-info/METADATA
mcp_xiaohongshu_kel-0.1.0.dist-info/WHEEL
mcp_xiaohongshu_kel-0.1.0.dist-info/entry_points.txt
mcp_xiaohongshu_kel-0.1.0.dist-info/RECORD
